{
  "id": "677e2720-91b4-4735-9eee-14a969beaec2",
  "createdAt": "2026-03-05T14:42:16.123Z",
  "variant": "testosterone",
  "name": "Johnny Lawrence",
  "answers": {
    "primaryConcerns": [
      "muscle_difficulty",
      "brain_fog"
    ],
    "muscleRecovery": true,
    "bodyFatPattern": "chest",
    "libidoMorningErections": false,
    "stressRecovery": true,
    "sleepQuality": "waking_night",
    "digestiveHealth": [
      "constipation",
      "diarrhea",
      "gas",
      "food_sensitivities"
    ],
    "energyLevel": 2,
    "coldExtremities": false,
    "typicalEating": "Oatmeal with fruit for breakfast. Sandwich and chips for lunch. Pasta with vegetables for dinner. Coffee throughout the day.",
    "healthGoals": "Improve gut health and reduce digestive issues. More mental clarity and focus."
  }
}